{
  "locked": false,
  "version": 2,
  "targets": {
    ".NETFramework,Version=v4.5.1": {
      "Microsoft.ServiceBus/1.0.0": {
        "type": "package",
        "frameworkAssemblies": [
          "Microsoft.CSharp",
          "mscorlib",
          "System",
          "System.Core"
        ],
        "compile": {
          "lib/net451/Microsoft.ServiceBus.dll": {}
        },
        "runtime": {
          "lib/net451/Microsoft.ServiceBus.dll": {}
        }
      }
    },
    ".NETFramework,Version=v4.5.1/win7-x86": {
      "Microsoft.ServiceBus/1.0.0": {
        "type": "package",
        "frameworkAssemblies": [
          "Microsoft.CSharp",
          "mscorlib",
          "System",
          "System.Core"
        ],
        "compile": {
          "lib/net451/Microsoft.ServiceBus.dll": {}
        },
        "runtime": {
          "lib/net451/Microsoft.ServiceBus.dll": {}
        }
      }
    },
    ".NETFramework,Version=v4.5.1/win7-x64": {
      "Microsoft.ServiceBus/1.0.0": {
        "type": "package",
        "frameworkAssemblies": [
          "Microsoft.CSharp",
          "mscorlib",
          "System",
          "System.Core"
        ],
        "compile": {
          "lib/net451/Microsoft.ServiceBus.dll": {}
        },
        "runtime": {
          "lib/net451/Microsoft.ServiceBus.dll": {}
        }
      }
    }
  },
  "libraries": {
    "Microsoft.ServiceBus/1.0.0": {
      "type": "package",
      "sha512": "Q6C8evaPJYgkwHHFtSCTNxFb+vzRz43pBZLLCqmidg7algl0iyduQAajLynNX2/pPB4WYc5Wqs1mJC+/kh6hkw==",
      "files": [
        "lib/net451/Microsoft.ServiceBus.dll",
        "Microsoft.ServiceBus.1.0.0.nupkg",
        "Microsoft.ServiceBus.1.0.0.nupkg.sha512",
        "Microsoft.ServiceBus.nuspec",
        "root/project.json",
        "root/project.lock.json"
      ]
    }
  },
  "projectFileDependencyGroups": {
    "": [
      "Microsoft.ServiceBus >= 1.0.0"
    ],
    ".NETFramework,Version=v4.5.1": []
  }
}